README.txt
setup.py
dronestore/__init__.py
dronestore/attribute.py
dronestore/merge.py
dronestore/model.py
dronestore/protocol.py
dronestore/query.py
dronestore/repo.py
dronestore.egg-info/PKG-INFO
dronestore.egg-info/SOURCES.txt
dronestore.egg-info/dependency_links.txt
dronestore.egg-info/requires.txt
dronestore.egg-info/top_level.txt
dronestore/ext/__init__.py
dronestore/ext/bottle/__init__.py
dronestore/ext/bottle/bottledronestore.py
dronestore/ext/bottle/test.py
dronestore/ext/web/__init__.py
dronestore/ext/web/forms.py
dronestore/util/__init__.py
dronestore/util/fasthash.py
dronestore/util/serial.py
test/test_attribute.py
test/test_merge.py
test/test_model.py
test/test_query.py
test/test_repo.py
test/test_serial.py
test/test_time.py