Metadata-Version: 1.0
Name: dronestore
Version: 0.2.8
Summary: DroneStore python implementation <http://dronestore.org/>
Home-page: http://github.com/jbenet/py-dronestore
Author: Juan Batiz-Benet
Author-email: juan@benet.ai
License: MIT License
Keywords: dronestore,data versioning
Platform: UNKNOWN
